turtle_art_manager/SizedTurtleArt.py
turtle_art_manager/__init__.py
turtle_art_manager/circle.py
turtle_art_manager/rectangle.py
turtle_art_manager/sized_turtle_art.py
turtle_art_manager/turtle_art.py
turtle_art_manager/turtle_draw.py
turtle_art_manager-1.5.dist-info/METADATA
turtle_art_manager-1.5.dist-info/WHEEL
turtle_art_manager-1.5.dist-info/top_level.txt
turtle_art_manager-1.5.dist-info/RECORD
