Metadata-Version: 2.1
Name: turtle-art-manager
Version: 1.5
Summary: A package for making turtle art
Home-page: https://github.com/FrickTzy/Turtle-Art
Author: FrickTzy (Kurt Arnoco)
Keywords: python,turtle,python turtle,python art
